{
  "slug": "primitive-fishing-survival",
  "versionId": "016b6464-585d-45e3-8d18-d07aa7d8bfd7",
  "versionNumber": 1,
  "reviewStatus": "draft",
  "isNew": true,
  "changeSummary": "New action_card for primitive fishing in survival situations. Covers passive weir construction, improvised hooks, dawn/dusk timing, field dressing, and cooking safety. sourceQuality: mixed. Warning: alternativeToGuideSlugs cross parentTopic boundaries — resolves as cluster grows.",
  "apiWarnings": [],
  "validationWarnings": [],
  "importedAt": "2026-03-16T09:14:31.626Z",
  "reviewUrl": "http://localhost:3000/review?filter=draft"
}